{ "defaultImg": "https://yt3.ggpht.com/-ZlIv92GuLBE/AAAAAAAAAAI/AAAAAAAAAAA/btOP2Mh8SEM/s88-c-k-no-rj-c0xffffff/photo.jpg", "videos": [{"title":"Syria Ramadan Programme 2016","position":0,"id":"R1eHfri5prY"},{"title":"\"Farming has stopped for over a year because of the drought\" - Hussein, Somalia","position":1,"id":"B5f1X0JvJiU"},{"title":"\"We are pastoralists \u0026 we have lost all our livestock\" - Efrah, Somalia","position":2,"id":"OSs6kd_cNg4"},{"title":"\"I have lost all of my livestock because of the drought\" - Zainab, Somalia","position":3,"id":"MycBGvZNj6E"},{"title":"\"Despite the conditions we still remain hopeful\" - Abdulrashid Ismail Jama, Somalia","position":4,"id":"qLQWADtV_go"},{"title":"Islamic Relief Borehole in Somalia","position":5,"id":"i49JJF8Xcug"},{"title":"I'm a Refugee","position":6,"id":"_e6hNo3Z66c"},{"title":"BBC World Service interview - Syria 13.9.2016","position":7,"id":"e1I7dPAAeVA"},{"title":"Aleppo Chlorine Attack","position":8,"id":"xn_TjsE3xR4"},{"title":"CEO Message - Eid Al Adha 2016","position":9,"id":"RSapv9bnifw"},{"title":"Qurbani - Syria","position":10,"id":"Wl9frFzYyo4"},{"title":"Islamic Relief: the numbers behind Yemen's war","position":11,"id":"Y4zsxxSIYjU"},{"title":"Islamic Relief - Aleppo Crisis 2016","position":12,"id":"JfWlhNiWGfo"},{"title":"A Beautiful Message","position":13,"id":"iSx4F24E61Y"},{"title":"Humanitarian Story: Ali","position":14,"id":"Cw9ANkwtNzc"},{"title":"Islamic Relief USA   #MyWinter #TheirWinter","position":15,"id":"X2slqLmYBgo"},{"title":"Islamic Relief Abdullah Shawky  After a Month in Paradise","position":16,"id":"vhJQpe6FYl8"},{"title":"A Refugee Story Untold  Batoul","position":17,"id":"JmjyfJiTdFQ"},{"title":"A Refugee Story Untold: Osama Shehadi","position":18,"id":"KNtu1nbIz2g"},{"title":"A Refugee Story Untold: Um Ahmed","position":19,"id":"fjkIdK2q1r0"},{"title":"A Refugee Story Untold","position":20,"id":"PUlqe9JLGE4"},{"title":"Find your meaningful career at Islamic Relief!","position":21,"id":"0EEMHVw_538"},{"title":"Universal Children's Day 2015","position":22,"id":"gA6wzyjpZl0"},{"title":"Islamic Relief reports from earthquake-hit areas","position":23,"id":"afIdnjRd2wE"},{"title":"Afghanistan and Pakistan Earthquake","position":24,"id":"aKLrTvL1jTI"},{"title":"Afghanistan and Pakistan Earthquake","position":25,"id":"JxT68lgdlKk"},{"title":"Eastern Afghanistan Earthquake","position":26,"id":"zxACSJJE9Ic"},{"title":"Adnan Cheema Speaks to CNN about Afghanistan \u0026 Pakistan Earthquake","position":27,"id":"3aXorULIERs"},{"title":"Islamic Relief Mediterranean Refugee Crisis: Case Study Mohammed","position":28,"id":"4-DUza1A7XM"},{"title":"Islamic Relief's Imran Madden interview with eNCA News channel","position":29,"id":"XWHmiHwx-Qw"},{"title":"Islamic Relief Day Two Mediterranean Refugee Crisis","position":30,"id":"uVKUEZfLVr8"},{"title":"Islamic Relief Emergency Response Team On The Greek Island of Lesvos","position":31,"id":"XVu0BpOgp3w"},{"title":"Remembering our colleagues World Humanitarian Day","position":32,"id":"uI7Z1mVXYFw"},{"title":"Dr Hany El-Banna Introduces World Humanitarian Day","position":33,"id":"Zgee9LIr9cs"},{"title":"Launch of the Islamic Climate Change Declaration - Press Conference","position":34,"id":"kMr9EHDXvyU"},{"title":"Launch of the Islamic Climate Change Declaration","position":35,"id":"wuN4mQ0-hB0"},{"title":"Praying For Home in Iraq","position":36,"id":"IfcF2aWzwVs"},{"title":"NMCH Virtual Tour","position":37,"id":"XuoEfvApQ1Q"},{"title":"Arbika, Chechnya | Islamic Relief Ramadan 2015","position":38,"id":"0UYvmJzjhEU"},{"title":"Khayryaah, Yemen | Islamic Relief Ramadan 2015","position":39,"id":"SUrJh9AaP2g"},{"title":"Wael, Gaza | Islamic Relief Ramadan 2015","position":40,"id":"dYzL3FTmEns"},{"title":"Hiba, Jordan | Islamic Relief Ramadan 2015","position":41,"id":"LoVfwvh2G00"},{"title":"Distributing #Ramadan food packs in #Syria","position":42,"id":"zhwXbeMezJk"},{"title":"Abu Basam, Syria | Islamic Relief Ramadan 2015","position":43,"id":"FqxBeI_3tLg"},{"title":"Jamila, Yemen | Islamic Relief Ramadan 2015","position":44,"id":"4p50ZFNPLbE"},{"title":"Um Mohammed, Syria | Islamic Relief Ramadan 2015","position":45,"id":"7jKpC8x9-Y0"},{"title":"Abo Abdo, Syria | Islamic Relief Ramadan 2015","position":46,"id":"Wer-1OqfGGQ"},{"title":"Um Omar, Syria | Islamic Relief Ramadan 2015","position":47,"id":"ss_pboBXxx4"},{"title":"Kawthar, Jordan | Islamic Relief Ramadan 2015","position":48,"id":"f_vOVtb4_-A"},{"title":"World Refugee Day | Islamic Relief Worldwide 2015","position":49,"id":"oFiAMgUu2Bs"},{"title":"Meet our global family | Islamic Relief Ramadan 2015","position":50,"id":"iRyCBW7RN34"},{"title":"Iraq in Crisis","position":51,"id":"m8IIOSdh9YM"},{"title":"Fatima, Lebanon | Islamic Relief Ramadan 2015","position":52,"id":"d_6I_kxM_ag"},{"title":"Hamidou, Syria | Islamic Relief Ramadan 2015","position":53,"id":"yEmdQRoFMs4"},{"title":"Iraq in Crisis: Islamic Relief aid worker reports from Iraq","position":54,"id":"MoOS5bzWQW4"},{"title":"Ramadan 2015 | Islamic Relief","position":55,"id":"0wc6pzNUoh4"},{"title":"Interview with Mohammed, Yemen","position":56,"id":"DrnOlZlPmAE"},{"title":"Akram - Islamic Relief Employee - Yemen Office","position":57,"id":"x4mrfKq9WlA"},{"title":"Sahar Salah - Islamic Relief Employee - Yemen Office","position":58,"id":"yWSAIBzbinQ"},{"title":"Saddam - Islamic Relief Employee - Yemen Office","position":59,"id":"os0QWJcdBpQ"},{"title":"Hisham - Islamic Relief Employee - Yemen Office","position":60,"id":"GCjpQsRLluQ"},{"title":"Ahmed Nahbal - Islamic Relief Employee - Yemen Office","position":61,"id":"nlBoTug5b1A"},{"title":"Islamic Relief - What we do","position":62,"id":"FqGQxj9Bk1U"},{"title":"Nepal Emergency Appeal 2015","position":63,"id":"biKYi19PzZk"},{"title":"Islamic Relief's response following Nepal's second devastating earthquake","position":64,"id":"SxgWYNkpwtk"},{"title":"Haseeb Khalid reports from Kathmandu airport - #Nepal","position":65,"id":"bhCOgXO0hNk"},{"title":"Islamic Relief - #Nepal Food Distribution","position":66,"id":"D4Ry2_MBr-s"},{"title":"Nepal Vlog - Islamic Relief's Head of Mission's update 28/4/2015","position":67,"id":"GABtUNhR120"},{"title":"Yemen Crisis Appeal 2015","position":68,"id":"pzmz6Zli7zQ"},{"title":"Islamic Relief's response to the Nepal earthquake","position":69,"id":"x6XcLeaT-xU"},{"title":"Yemen crisis appeal: Reports from Sana'a","position":70,"id":"vrf9eFJeZr0"},{"title":"Islamic Relief - Pay Attention","position":71,"id":"4R3Nz4E2U4M"},{"title":"Syria: Islamic Relief's work throughout four years of conflict","position":72,"id":"IvyaWztftKc"},{"title":"Iraq emergency response: aid for displaced families","position":73,"id":"msA5neKivHw"},{"title":"2004 Tsunami: 10 years on","position":74,"id":"mcGr7440fDk"},{"title":"2004 Tsunami: 10 years on","position":75,"id":"8nl_0_ns7e4"},{"title":"IR IDB HAITI","position":76,"id":"-ePVN9cSOeY"},{"title":"Qurbani Project 2014","position":77,"id":"9EzB4oov6-U"},{"title":"CAR Child Friendly Spaces","position":78,"id":"vKuvsAIjMJU"},{"title":"CAR child friendly spaces","position":79,"id":"Msk4dVni5NE"},{"title":"نداء استغاثة لفلسطين - هذا نداء استغاثة من الإغاثة الإسلامية، نأمل أن تعطوا كلَّ ما في وُسعكم.","position":80,"id":"wnIPouOa6qA"},{"title":"Palestine Emergency Appeal","position":81,"id":"gmFQVnmcIoI"},{"title":"حملة أنا وكافل اليتيم - الإغاثة الإسلامية عبر العالم -","position":82,"id":"-rIA-fnfcd8"},{"title":"حملة أنا وكافل اليتيم - الإغاثة الإسلامية عبر العالم","position":83,"id":"qBkwbBnsVec"},{"title":"RAMADAN APPEAL 2014 SHAHZEB FROM PAKISTAN","position":84,"id":"Ia4iKxjGARQ"},{"title":"RAMADAN APPEAL 2014 EYE HOSPITAL","position":85,"id":"DxAFCTtlNs4"},{"title":"Ramadan 2014 Appeal Power of Zakat","position":86,"id":"0PzMz4LXQmw"},{"title":"Ramadan 2014 Appeal Zakat and Orphans","position":87,"id":"uXpNlsnY6mg"},{"title":"Ramadan 2014 رمضان","position":88,"id":"R_1Vxpm4cOY"},{"title":"Syria Ramadan 2014","position":89,"id":"pKzkOHgA1TU"},{"title":"Fight childhood cancer in Africa","position":90,"id":"5K-_xrQtP7o"},{"title":"Ramadan 2014","position":91,"id":"bs0PwZzZB1M"},{"title":"The Gift of Qurbani - Douda","position":92,"id":"DZxkdtizEas"},{"title":"The Gift of Qurbani - Boubacar","position":93,"id":"t3oPd3fo3uc"},{"title":"Philippines Emergency - One Month On","position":94,"id":"xovRtB3Sj-I"},{"title":"Islamic Relief Qurbani 2013","position":95,"id":"l5jE9hB0Nes"},{"title":"Yemen Livelihoods: Khalid's story","position":96,"id":"OJ2_ms7s1-c"},{"title":"Into The Light (a true story about the huge impact of eye cataract surgery)","position":97,"id":"3knQm2uej6k"},{"title":"Niger: Guardians","position":98,"id":"5CzmwemaS0Q"},{"title":"Gaza: Community Health Centre","position":99,"id":"PPm1yjLBUco"},{"title":"Ramadan with Islamic Relief","position":100,"id":"97fFJgWZYmM"},{"title":"Ramadan 2013: A Thank You Message","position":101,"id":"YxIvc93_87Q"},{"title":"Ramadan 2013: War on Hunger","position":102,"id":"Vu0souEQKMU"},{"title":"Clip 2: Children from South Africa taking part in the Global Day of Action for Hunger","position":103,"id":"q28ObpqQp20"},{"title":"Clip: Children from South Africa taking part in the Global Day of Action for Hunger","position":104,"id":"eA2j_shSwRE"},{"title":"Syria Alkarama Camp","position":105,"id":"WQvy8F6KvvY"},{"title":"Mali: Rural Maternity","position":106,"id":"Y2sPEX9ZQBM"},{"title":"Syria: Two Years, Too Long","position":107,"id":"eEJzLzN8H7U"},{"title":"The Harvest","position":108,"id":"OPlGDVpx7ME"},{"title":"Day 03 Synergising Resilience","position":109,"id":"20Zq6nATXXA"},{"title":"Strengthening Disaster Preparedness Event, Pakistan Day 2","position":110,"id":"faaM-OrZejg"},{"title":"Islamic Relief's Qah Refugee Camp, Syria","position":111,"id":"ZYosXCih35A"},{"title":"Synergizing Resilience: Day Two","position":112,"id":"U7ODJWnvlSo"},{"title":"Enough Food For Everyone IF","position":113,"id":"psRyg0qbNOA"},{"title":"Join the team at Islamic Relief","position":114,"id":"D-TJ4x3mek4"},{"title":"Feeling the heat: Join the discussion","position":115,"id":"gcNKyIg9y3g"},{"title":"Medical Intervention inside Syria","position":116,"id":"vq5dkizRHhk"},{"title":"Feeling The Heat: Climate Change and it's impact on the poor","position":117,"id":"W1EKkV11YwU"},{"title":"Gaza Emergency 22 November 2012","position":118,"id":"ONIGaAKdggs"},{"title":"IRW Qurbani Video 2012","position":119,"id":"gaAh0o4aEUk"},{"title":"Syria Video October 2012","position":120,"id":"1Ae4O4SP59w"},{"title":"In Hope of a Harvest","position":121,"id":"MEAffrBJ16s"},{"title":"Ramadan appeal 2012 (Palestine) Every Second Counts","position":122,"id":"mM4qqiGvOhU"},{"title":"Ramadan appeal 2012 (Indonesia) Every Second Counts","position":123,"id":"N_JU3wl239Q"},{"title":"Ramadan appeal 2012 (Bangladesh) - Every Second Counts","position":124,"id":"TTOKN15KOEo"},{"title":"In Hope of a Harvest","position":125,"id":"cd9bgETRqcE"},{"title":"Islamic Relief provides medical aid in Homs","position":126,"id":"KT5EB2LfZXw"},{"title":"Syrian family living in an animal shelter","position":127,"id":"qURsb_ASIac"},{"title":"Syrian refugee stories","position":128,"id":"DNsb7RThQg4"},{"title":"Syria's cry for help","position":129,"id":"nQpuZ0txBcA"},{"title":"Islamic Relief: Emergency Relief for Syrian Refugees","position":130,"id":"bxjaUNJmHpE"},{"title":"Haiti - Two years on","position":131,"id":"hgvWZHtMaIA"},{"title":"Pakistan Floods Pt4","position":132,"id":"C5uENpFRRqs"},{"title":"Pakistan Floods Pt3","position":133,"id":"Ys6ksVsnrrs"},{"title":"Pakistan Floods Pt2","position":134,"id":"86gTtsQGZko"},{"title":"Pakistan Floods Pt1","position":135,"id":"jVWtBbGUisA"},{"title":"Latest situation of Sindh Floods 2011","position":136,"id":"Hb0NO3804Mk"},{"title":"Pakistan Flood One Year On:","position":137,"id":"GihxKr6IFZk"},{"title":"Pakistan Floods 2011: Islamic Relief rescues family trapped in flood hit village","position":138,"id":"r586m4van_k"},{"title":"Libya crisis: Islamic Relief take over management of UNHCR refugee camp","position":139,"id":"xG2adxzbfac"},{"title":"Islamic Relief carries out a rapid needs assessment in Tripoli","position":140,"id":"XaH4Xy-j_CQ"},{"title":"Genius Aulaid and Raihan Ramadan Music Video for Islamic Relief","position":141,"id":"16Jj_5GQjas"},{"title":"East Africa Crisis: UK Fundraiser visits Kenya","position":142,"id":"nvoVDcEMP80"},{"title":"East Africa Crisis: CEO Saleh Saeed in Kenya","position":143,"id":"pKu5OkydATs"},{"title":"East Africa Crisis: An Analysis","position":144,"id":"1bw1o3U2EFk"},{"title":"East Africa Crisis: Canadian Medical team treating patients in Mogadishu","position":145,"id":"_6gm94FegVM"},{"title":"East Africa Crisis: IDP camp in Mogadishu","position":146,"id":"8PckyF_OwsU"},{"title":"East Africa Crisis: Emergency food distribution in Somalia","position":147,"id":"Z3NR8rONJX8"},{"title":"Islamic Relief: Shelter advert for Ramadan 2011","position":148,"id":"l0EsIwEl45w"},{"title":"Islamic Relief: Shelter advert for Ramadan 2011 (short version)","position":149,"id":"6fe4S3dloas"},{"title":"Islamic Relief: Education advert for Ramadan 2011","position":150,"id":"XVHKSQ9UNlU"},{"title":"Islamic Relief: Education advert for Ramadan 2011 (short version)","position":151,"id":"QYPmfdxnTsg"},{"title":"Imam Zaid Shakir Ramadan Preperation part 2","position":152,"id":"w7aLwZq5Mnk"},{"title":"Imam Zaid Shakir Ramadan Preperation part 1","position":153,"id":"BfdnClKUGII"},{"title":"Imam Zaid Shakir Ramadan Preperation part 7","position":154,"id":"iu8Vu_w33uk"},{"title":"Photo gallery: Palestine Education","position":155,"id":"JJywZdBLFXE"},{"title":"Photo Gallery: Kenya Water Projects","position":156,"id":"d3Q1uOCm_tg"},{"title":"Imam Zaid Shakir Ramadan Preperation part 6","position":157,"id":"2vSP_cAuluU"},{"title":"Photo Gallery: Indonesia Education","position":158,"id":"jf4Jw6Hy8kY"},{"title":"Imam Zaid Shakir Ramadan Preperation part 5","position":159,"id":"0DFFyyqdGQM"},{"title":"Imam Zaid Shakir Ramadan Preperation part 3","position":160,"id":"kKVcdAAGUM4"},{"title":"Imam Zaid Shakir Ramadan Preperation part 4","position":161,"id":"M6qsn6lGYNI"},{"title":"Photo Gallery: Water projects in Sindh, Pakistan","position":162,"id":"OBB4iD9JWZg"},{"title":"Photo Gallery: Education in Sindh","position":163,"id":"D-7MYnbKFWQ"},{"title":"Photo Gallery Livlihood Punjab","position":164,"id":"Dwdfn257fzI"},{"title":"Photo Gallery: Indonesia Livelihood","position":165,"id":"JX-_9no7QFA"},{"title":"Improving lives in Balochistan: with Fadlullah Wilmot, the Director of Islamic Relief Pakistan","position":166,"id":"vq5iip2icM0"},{"title":"Director of Islamic Relief Pakistan talks about Microfinance","position":167,"id":"Cvj9dTyNzd0"},{"title":"Islamic Relief's Aid Operations in Western Libya","position":168,"id":"IhTOl0Fff54"},{"title":"Islamic Relief on Midlands Today - Pakistan 3","position":169,"id":"a2PraYYZoM8"},{"title":"Islamic Relief on BBC Midlands Today- Pakistani floods 2","position":170,"id":"a1P1ihFDKWE"},{"title":"Islamic Relief on BBC Midlands Today - Pakistan floods","position":171,"id":"WBTmHGAkrvA"},{"title":"Libya update 23rd April","position":172,"id":"g_lZDlcTDmo"},{"title":"Moustafa Osman in UNHCR's ramada camp in Tunisia","position":173,"id":"qquJp9nCYNE"},{"title":"Islamic Relief on the Libyan Tunisian border","position":174,"id":"gwK7Ii9-d7c"},{"title":"What is Islamic Relief doing now?","position":175,"id":"nrGSEiwRXtY"},{"title":"Islamic Relief Italy at the Ras Jdir Camp, Libya","position":176,"id":"aAMzF3IGYDI"},{"title":"Panorama of the Tunisia / Libya border","position":177,"id":"6f9twsuQNIg"},{"title":"Islamic Relief Medical Warehouse in Libya","position":178,"id":"2zsfz08K7Bg"},{"title":"A quick message from our team in Libya","position":179,"id":"-28dAbW1MNA"},{"title":"Islamic Relief Aid Worker in Libya:","position":180,"id":"Jcc4b-GK0lM"},{"title":"A Message from Saleh Saeed CEO Islamic Relief Worldwide","position":181,"id":"gXuF1xPEiOU"},{"title":"From Flood to a Future:  Islamic Relief in Lunda, Pakistan","position":182,"id":"aLi09zdRKSM"},{"title":"Women's Nurse Helps the Victims of the Pakistan Flood","position":183,"id":"4heY630rWhY"},{"title":"Jehangir Malik at village Lunda Charsadda","position":184,"id":"1i5vVThZA88"},{"title":"Distributing Hygiene Kits","position":185,"id":"YbfREjv25rA"},{"title":"Meeting with Beneficiaries in Pakistan","position":186,"id":"vUrN16wFYzA"},{"title":"Interview with Islamic Relief Pakistan Aid Worker","position":187,"id":"pUeWRiOFW5I"},{"title":"Pakistan Flood: Food Packs","position":188,"id":"qvYQ8RriWXo"},{"title":"Islamic Relief's Waqf Future Fund","position":189,"id":"6P9qL9fuwjM"},{"title":"Our Aid Worker Speaks to a Survivor in Haiti","position":190,"id":"mjPcss7kjwg"},{"title":"Haiti Water Project","position":191,"id":"tbDYJd4xVZA"},{"title":"HRH Prince Charles Gala Dinner Speech","position":192,"id":"MTU7_K5cLpM"},{"title":"Bangladesh Livelihood 30 Sec","position":193,"id":"D6CUVXUXXJs"},{"title":"Bangladesh Livelihood: Islamic Relief","position":194,"id":"5Z8A0F_C5_A"},{"title":"Water \u0026 Sanitation in Mali: Islamic Relief. 60 sec","position":195,"id":"Mf8ZR62JM8E"},{"title":"Water \u0026 Sanitation in Mali:  Islamic Relief.   30 sec","position":196,"id":"qfJpQALgx9U"},{"title":"Islamic Relief: Education in Mali","position":197,"id":"dZjQufnBX_g"},{"title":"The only centre for artificial limbs (prosthesis) in Gaza - Islamic Relief Worldwide","position":198,"id":"o6Qv9SbrfNs"},{"title":"Islamic Relief 25th Annivesary advert","position":199,"id":"Cv6FvIFnG8w"},{"title":"Gaza Vid Blog 2: Islamic Relief","position":200,"id":"fEuxaOvbXU8"},{"title":"Gaza Vid Blog: Islamic Relief","position":201,"id":"6YOZc5lwpTk"},{"title":"Islamic Relief: Who We Are","position":202,"id":"pPxkhznXxVw"},{"title":"Islamic Relief: Where We Work","position":203,"id":"1ZPoE5JhH7k"},{"title":"Islamic Relief:  What We Do","position":204,"id":"xWZFVmrXFTA"},{"title":"Perform the Blessed Qurbani with Remembrance --Islamic Relief","position":205,"id":"RUuOsNKGK5Q"},{"title":"The reward of Qurbani -- Islamic Relief","position":206,"id":"oYlKgiF5scU"},{"title":"IRs Qurbani Programme reaches over 2 million people","position":207,"id":"b9JyPgKd-X4"},{"title":"Ramadhan - Islamic Relief","position":208,"id":"ndcvCLPdbYg"},{"title":"The Rain Prayer Miracle:  Islamic Relief","position":209,"id":"IcoKuEL9Pmc"},{"title":"Take Action for Africa! - Islamic Relief","position":210,"id":"3wKzJrC2izY"},{"title":"Children and Poverty -- Islamic Relief","position":211,"id":"Apv5B4yFbfQ"},{"title":"Poverty and Powerlessness for Women - Islamic Relief","position":212,"id":"orPpyq-A4JU"},{"title":"Poverty and Powerlessness - Islamic Relief","position":213,"id":"PZAcktgwuS8"},{"title":"Action for Africa 2007:  Islamic Relief","position":214,"id":"oUzjS1anPPQ"},{"title":"Islamic Relief - What's happening to children in Iraq","position":215,"id":"f0ACL3DlTX8"}] }