[{"title":"Afghanistan","iso3":"afg","id":"PLis1OTL4y_TTBtG-2EWc8vfVNG0RuoSFG","defaultImg":"http:\/\/img.static.reliefweb.int\/sites\/reliefweb.int\/files\/country-icons\/afg.png"},{"title":"Bangladesh","iso3":"bgd","id":"PLis1OTL4y_TSCyRfb-b60-DEpu29_Z6Sl","defaultImg":"http:\/\/img.static.reliefweb.int\/sites\/reliefweb.int\/files\/country-icons\/bgd.png"},{"title":"Burkina Faso","iso3":"bfa","id":"PLis1OTL4y_TSf4dWcXOKCIYdjXlvcVFnQ","defaultImg":"http:\/\/img.static.reliefweb.int\/sites\/reliefweb.int\/files\/country-icons\/bfa.png"},{"title":"Burundi","iso3":"bdi","id":"PLis1OTL4y_TSORyBnBha2kS2TyS9SFjRI","defaultImg":"http:\/\/img.static.reliefweb.int\/sites\/reliefweb.int\/files\/country-icons\/bdi.png"},{"title":"Cameroon","iso3":"cmr","id":"PLis1OTL4y_TSwPBHwFsiG4XDA9wFHjTlC","defaultImg":"http:\/\/img.static.reliefweb.int\/sites\/reliefweb.int\/files\/country-icons\/cmr.png"},{"title":"Central African Republic","iso3":"caf","id":"PLis1OTL4y_TR0zDzjXGQHfuHhiSB2LBGC","defaultImg":"http:\/\/img.static.reliefweb.int\/sites\/reliefweb.int\/files\/country-icons\/caf.png"},{"title":"Chad","iso3":"tcd","id":"PLis1OTL4y_TSv4xVKw5GzTbp__s0ubhFA","defaultImg":"http:\/\/img.static.reliefweb.int\/sites\/reliefweb.int\/files\/country-icons\/tcd.png"},{"title":"Colombia","iso3":"col","id":"PLis1OTL4y_TStO_DnWATODO2Ww1paMQt6","defaultImg":"http:\/\/img.static.reliefweb.int\/sites\/reliefweb.int\/files\/country-icons\/col.png"},{"title":"Democratic Republic of the Congo","iso3":"cod","id":"PLis1OTL4y_TQEGuosjGpzW5t2DivJknzh","defaultImg":"http:\/\/img.static.reliefweb.int\/sites\/reliefweb.int\/files\/country-icons\/cod.png"},{"title":"Ethiopia","iso3":"eth","id":"PLis1OTL4y_TRgu8-zGyBQ8S9u0mg06FBi","defaultImg":"http:\/\/img.static.reliefweb.int\/sites\/reliefweb.int\/files\/country-icons\/eth.png"},{"title":"Fiji","iso3":"fji","id":"PLis1OTL4y_TToKBXyiv1Gl4XuihCKY72W","defaultImg":"http:\/\/img.static.reliefweb.int\/sites\/reliefweb.int\/files\/country-icons\/fji.png"},{"title":"Guatemala","iso3":"gtm","id":"PLis1OTL4y_TRnbaqPYcGXLOfZ-5Is9uTx","defaultImg":"http:\/\/img.static.reliefweb.int\/sites\/reliefweb.int\/files\/country-icons\/gtm.png"},{"title":"Guinea","iso3":"gin","id":"PLis1OTL4y_TSLvTextvJkAh8G7vsJ8WNW","defaultImg":"http:\/\/img.static.reliefweb.int\/sites\/reliefweb.int\/files\/country-icons\/gin.png"},{"title":"Haiti","iso3":"hti","id":"PLis1OTL4y_TRLuABgqJkHaOBdi3fFNK5T","defaultImg":"http:\/\/img.static.reliefweb.int\/sites\/reliefweb.int\/files\/country-icons\/hti.png"},{"title":"Indonesia","iso3":"idn","id":"PLis1OTL4y_TQPLo7pgZz54UfrTHQWjQcu","defaultImg":"http:\/\/img.static.reliefweb.int\/sites\/reliefweb.int\/files\/country-icons\/idn.png"},{"title":"Iraq","iso3":"irq","id":"PLis1OTL4y_TRCxDCZ4I1zRvGNDCBeBlxh","defaultImg":"http:\/\/img.static.reliefweb.int\/sites\/reliefweb.int\/files\/country-icons\/irq.png"},{"title":"Jordan","iso3":"jor","id":"PLis1OTL4y_TTPqnGag4KSRk7KhAz65IlI","defaultImg":"http:\/\/img.static.reliefweb.int\/sites\/reliefweb.int\/files\/country-icons\/jor.png"},{"title":"Kenya","iso3":"ken","id":"PLis1OTL4y_TTwDCwdcw5sSjuMfrgB8lwj","defaultImg":"http:\/\/img.static.reliefweb.int\/sites\/reliefweb.int\/files\/country-icons\/ken.png"},{"title":"Lebanon","iso3":"lbn","id":"PLis1OTL4y_TRkEf94DCe_gjVxOcHxjTJX","defaultImg":"http:\/\/img.static.reliefweb.int\/sites\/reliefweb.int\/files\/country-icons\/lbn.png"},{"title":"Liberia","iso3":"lbr","id":"PLis1OTL4y_TRDeRRuy4uP58m0K_KDapQO","defaultImg":"http:\/\/img.static.reliefweb.int\/sites\/reliefweb.int\/files\/country-icons\/lbr.png"},{"title":"Libya","iso3":"lby","id":"PLis1OTL4y_TQ6FFZZVt_7B8QD6nZumrrW","defaultImg":"http:\/\/img.static.reliefweb.int\/sites\/reliefweb.int\/files\/country-icons\/lby.png"},{"title":"Malawi","iso3":"mwi","id":"PLis1OTL4y_TRuMT8pUEA74SoTW-riCZgU","defaultImg":"http:\/\/img.static.reliefweb.int\/sites\/reliefweb.int\/files\/country-icons\/mwi.png"},{"title":"Mali","iso3":"mli","id":"PLis1OTL4y_TT4Cml4WarDwVci0xrzyuJa","defaultImg":"http:\/\/img.static.reliefweb.int\/sites\/reliefweb.int\/files\/country-icons\/mli.png"},{"title":"Mauritania","iso3":"mrt","id":"PLis1OTL4y_TQUB-cZhaQKAq1wMrwzu3_T","defaultImg":"http:\/\/img.static.reliefweb.int\/sites\/reliefweb.int\/files\/country-icons\/mrt.png"},{"title":"Myanmar","iso3":"mmr","id":"PLis1OTL4y_TRcUI8AOv97SFAV947lf8sg","defaultImg":"http:\/\/img.static.reliefweb.int\/sites\/reliefweb.int\/files\/country-icons\/mmr.png"},{"title":"Nepal","iso3":"npl","id":"PLis1OTL4y_TTA86NpcRkFvpmNfwZPmtHm","defaultImg":"http:\/\/img.static.reliefweb.int\/sites\/reliefweb.int\/files\/country-icons\/npl.png"},{"title":"Niger","iso3":"ner","id":"PLis1OTL4y_TTV82-p4of1wFqFK-tjZ1xS","defaultImg":"http:\/\/img.static.reliefweb.int\/sites\/reliefweb.int\/files\/country-icons\/ner.png"},{"title":"Nigeria","iso3":"nga","id":"PLis1OTL4y_TSvNpsUATNOW1-0Fg3E5B-h","defaultImg":"http:\/\/img.static.reliefweb.int\/sites\/reliefweb.int\/files\/country-icons\/nga.png"},{"title":"occupied Palestinian territory","iso3":"pse","id":"PLis1OTL4y_TS8Eit7apyxhMN-0CmMUuiz","defaultImg":"http:\/\/img.static.reliefweb.int\/sites\/reliefweb.int\/files\/country-icons\/pse.png"},{"title":"Pakistan","iso3":"pak","id":"PLis1OTL4y_TSsMj8rIJFT8LU7BwAiEAeu","defaultImg":"http:\/\/img.static.reliefweb.int\/sites\/reliefweb.int\/files\/country-icons\/pak.png"},{"title":"Philippines","iso3":"phl","id":"PLis1OTL4y_TSR-n70eN53JwCJYl4YoXu5","defaultImg":"http:\/\/img.static.reliefweb.int\/sites\/reliefweb.int\/files\/country-icons\/phl.png"},{"title":"Sierra Leone","iso3":"sle","id":"PLis1OTL4y_TT7romfakPdUA_WEsZsFHkJ","defaultImg":"http:\/\/img.static.reliefweb.int\/sites\/reliefweb.int\/files\/country-icons\/sle.png"},{"title":"Somalia","iso3":"som","id":"PLis1OTL4y_TSu7khwN7YIdBzIgSblILuw","defaultImg":"http:\/\/img.static.reliefweb.int\/sites\/reliefweb.int\/files\/country-icons\/som.png"},{"title":"South Sudan","iso3":"ssd","id":"PLis1OTL4y_TQP9qiTk-M0xzgukD-WoJ-U","defaultImg":"http:\/\/img.static.reliefweb.int\/sites\/reliefweb.int\/files\/country-icons\/ssd.png"},{"title":"Sri Lanka","iso3":"lka","id":"PLis1OTL4y_TRMsGtVybalbi-LnpacX6vC","defaultImg":"http:\/\/img.static.reliefweb.int\/sites\/reliefweb.int\/files\/country-icons\/lka.png"},{"title":"Sudan","iso3":"sdn","id":"PLis1OTL4y_TRJvQCnZIkZctzISPKwAXeY","defaultImg":"http:\/\/img.static.reliefweb.int\/sites\/reliefweb.int\/files\/country-icons\/sdn.png"},{"title":"Syrian Arab Republic","iso3":"syr","id":"PLis1OTL4y_TRijlRTJPAbOfSMOHo2eFLS","defaultImg":"http:\/\/img.static.reliefweb.int\/sites\/reliefweb.int\/files\/country-icons\/syr.png"},{"title":"Turkey","iso3":"tur","id":"PLis1OTL4y_TRNxJdX_IY0YltlP0UIK6_W","defaultImg":"http:\/\/img.static.reliefweb.int\/sites\/reliefweb.int\/files\/country-icons\/tur.png"},{"title":"Ukraine","iso3":"ukr","id":"PLis1OTL4y_TQQ1Wq1sCOU5PE1g59TrEK4","defaultImg":"http:\/\/img.static.reliefweb.int\/sites\/reliefweb.int\/files\/country-icons\/ukr.png"},{"title":"Vanuatu","iso3":"vut","id":"PLis1OTL4y_TTwdeThdriK6Mtfth0DzZRc","defaultImg":"http:\/\/img.static.reliefweb.int\/sites\/reliefweb.int\/files\/country-icons\/vut.png"},{"title":"Yemen","iso3":"yem","id":"PLis1OTL4y_TQMrX9XO_8gZ6RMOsy0LpnW","defaultImg":"http:\/\/img.static.reliefweb.int\/sites\/reliefweb.int\/files\/country-icons\/yem.png"},{"title":"Zimbabwe","iso3":"zwe","id":"PLis1OTL4y_TRpo_sT4avsYj3cUVqPPAwI","defaultImg":"http:\/\/img.static.reliefweb.int\/sites\/reliefweb.int\/files\/country-icons\/zwe.png"}]